cheshire_orca-0.3.1.dist-info/licenses/LICENSE
orca/__init__.py
orca/config_interfaces.py
orca/helper.py
orca/orca_core.py
orca/orca_entry.py
orca/cli/__init__.py
orca/cli/orca_api.py
orca/cli/orca_cli.py
orca/cli/orca_rest_api.py
orca/cli/socketio_mount.py
orca/driver_management/__init__.py
orca/driver_management/driver_installer.py
orca/driver_management/driver_socket_client.py
orca/driver_management/drivers/__init__.py
orca/driver_management/drivers/null_plate_pad/__init__.py
orca/driver_management/drivers/null_plate_pad/null_plate_pad.py
orca/driver_management/drivers/simulation_base/__init__.py
orca/driver_management/drivers/simulation_base/simulation_base.py
orca/driver_management/drivers/simulation_labware_placeable/__init__.py
orca/driver_management/drivers/simulation_labware_placeable/simulation_labware_placeable.py
orca/driver_management/drivers/simulation_robotic_arm/__init__.py
orca/driver_management/drivers/simulation_robotic_arm/human_transfer.py
orca/driver_management/drivers/simulation_robotic_arm/simulation_robotic_arm.py
orca/events/event_bus.py
orca/events/event_bus_interface.py
orca/events/event_handler_interface.py
orca/events/event_handlers.py
orca/events/execution_context.py
orca/logger/socketio_logger_handler.py
orca/resource_models/__init__.py
orca/resource_models/base_resource.py
orca/resource_models/device_error.py
orca/resource_models/labware.py
orca/resource_models/location.py
orca/resource_models/plate_pad.py
orca/resource_models/resource_pool.py
orca/resource_models/transporter_resource.py
orca/resource_models/resource_extras/__init__.py
orca/resource_models/resource_extras/teachpoints.py
orca/scripting/__init__.py
orca/scripting/scripting.py
orca/sdk/__init__.py
orca/sdk/devices.py
orca/sdk/drivers.py
orca/sdk/events.py
orca/sdk/labware.py
orca/sdk/system.py
orca/sdk/workflow.py
orca/system/SdkToSystemBuilder.py
orca/system/__init__.py
orca/system/executors.py
orca/system/interfaces.py
orca/system/labware_registry_interfaces.py
orca/system/registries.py
cheshire_orca-0.3.1.dist-info/METADATA
cheshire_orca-0.3.1.dist-info/WHEEL
cheshire_orca-0.3.1.dist-info/entry_points.txt
cheshire_orca-0.3.1.dist-info/top_level.txt
cheshire_orca-0.3.1.dist-info/RECORD
