Metadata-Version: 2.4
Name: cheshire-orca
Version: 0.3.1
Summary: Laboratory Automation Framework
Author-email: Cheshire Labs <support@cheshirelabs.io>
License: AGPL-3.0-only
Project-URL: Repository, https://github.com/Cheshire-Labs/orca
Classifier: Programming Language :: Python :: 3.10
Classifier: License :: OSI Approved :: GNU Affero General Public License v3
Classifier: Operating System :: OS Independent
Requires-Python: >=3.10
License-File: LICENSE
Requires-Dist: colorama>=0.4.6
Requires-Dist: pydantic>=2.7.4
Requires-Dist: python-socketio>=5.11.2
Requires-Dist: networkx>=3.3
Requires-Dist: matplotlib>=3.9.0
Requires-Dist: PyYAML>=6.0.1
Requires-Dist: requests>=2.32.3
Requires-Dist: orca-interfaces>=0.1.0
Requires-Dist: fastapi>=0.70.0
Requires-Dist: uvicorn>=0.15.0
Provides-Extra: dev
Requires-Dist: pytest>=7.3.1; extra == "dev"
Requires-Dist: types-PyYAML; extra == "dev"
Requires-Dist: types-setuptools; extra == "dev"
Requires-Dist: black; extra == "dev"
Dynamic: license-file
